pyfactories/__init__.py
pyfactories/exceptions.py
pyfactories/factory.py
pyfactories/fields.py
pyfactories/protocols.py
pyfactories/py.typed
pyfactories/utils.py
pyfactories/constraints/__init__.py
pyfactories/constraints/collection.py
pyfactories/constraints/date.py
pyfactories/constraints/decimal.py
pyfactories/constraints/float.py
pyfactories/constraints/integer.py
pyfactories/constraints/strings.py
pyfactories/extensions/__init__.py
pyfactories/extensions/beanie_odm.py
pyfactories/extensions/odmantic_odm.py
pyfactories/extensions/ormar_orm.py
pyfactories/plugins/__init__.py
pyfactories/plugins/pytest_plugin.py
pyfactories/value_generators/__init__.py
pyfactories/value_generators/complex_types.py
pyfactories/value_generators/constrained_number.py
pyfactories/value_generators/primitives.py
pyfactories/value_generators/regex.py
pyfactories-2.0.0.dist-info/METADATA
pyfactories-2.0.0.dist-info/WHEEL
pyfactories-2.0.0.dist-info/licenses/LICENSE
pyfactories-2.0.0.dist-info/RECORD
