Metadata-Version: 2.1
Name: pyfactories
Version: 2.0.0
Summary: Mock data generation for pydantic and dataclasses
Project-URL: Homepage, https://github.com/tarsil/pyfactories
Project-URL: Documentation, https://pyfactories.tarsild.io
Project-URL: Changelog, https://pyfactories.tarsild.io/release-notes/
Project-URL: Funding, https://github.com/sponsors/tarsil
Project-URL: Source, https://github.com/tarsil/pyfactories
Author-email: Tiago Silva <tiago.arasilva@gmail.com>
License-Expression: MIT
License-File: LICENSE
Keywords: pyfactories
Classifier: Development Status :: 4 - Beta
Classifier: Environment :: Web Environment
Classifier: Framework :: AnyIO
Classifier: Framework :: AsyncIO
Classifier: Intended Audience :: Developers
Classifier: Intended Audience :: Information Technology
Classifier: Intended Audience :: System Administrators
Classifier: License :: OSI Approved :: MIT License
Classifier: Operating System :: OS Independent
Classifier: Programming Language :: Python
Classifier: Programming Language :: Python :: 3
Classifier: Programming Language :: Python :: 3 :: Only
Classifier: Programming Language :: Python :: 3.8
Classifier: Programming Language :: Python :: 3.9
Classifier: Programming Language :: Python :: 3.10
Classifier: Programming Language :: Python :: 3.11
Classifier: Topic :: Internet
Classifier: Topic :: Internet :: WWW/HTTP
Classifier: Topic :: Internet :: WWW/HTTP :: HTTP Servers
Classifier: Topic :: Software Development
Classifier: Topic :: Software Development :: Libraries
Classifier: Topic :: Software Development :: Libraries :: Application Frameworks
Classifier: Topic :: Software Development :: Libraries :: Python Modules
Classifier: Typing :: Typed
Requires-Python: >=3.8
Requires-Dist: faker<30.0.0,>=18.11.1
Requires-Dist: pydantic-extra-types<3.0.0,>=2.0.0
Requires-Dist: pydantic<3.0.0,>=2.0.0
Requires-Dist: typing-extensions<7.0.0,>=4.6.3
Provides-Extra: dev
Requires-Dist: email-validator<4.0.0,>=2.0.0.post2; extra == 'dev'
Requires-Dist: hypothesis<7.0.0,>=6.79.1; extra == 'dev'
Requires-Dist: ipdb<1.0.0,>=0.13.13; extra == 'dev'
Requires-Dist: pre-commit<4.0.0,>=3.3.1; extra == 'dev'
Provides-Extra: doc
Requires-Dist: mdx-include<2.0.0,>=1.4.1; extra == 'doc'
Requires-Dist: mkautodoc<0.3.0,>=0.2.0; extra == 'doc'
Requires-Dist: mkdocs-markdownextradata-plugin<0.3.0,>=0.1.7; extra == 'doc'
Requires-Dist: mkdocs-material==9.1.5; extra == 'doc'
Requires-Dist: mkdocs<2.0.0,>=1.4.2; extra == 'doc'
Requires-Dist: mkdocstrings<0.21.0,>=0.19.0; extra == 'doc'
Requires-Dist: pyyaml<7.0.0,>=5.3.1; extra == 'doc'
Provides-Extra: test
Requires-Dist: autoflake<3.0.0,>=2.0.2; extra == 'test'
Requires-Dist: black<24.0.0,>=23.3.0; extra == 'test'
Requires-Dist: isort<6.0.0,>=5.12.0; extra == 'test'
Requires-Dist: mypy<2.0.0,>=1.1.0; extra == 'test'
Requires-Dist: pytest-asyncio<1.0.0,>=0.21.0; extra == 'test'
Requires-Dist: pytest-cov<5.0.0,>=4.0.0; extra == 'test'
Requires-Dist: pytest<8.0.0,>=7.2.2; extra == 'test'
Requires-Dist: requests>=2.28.2; extra == 'test'
Requires-Dist: ruff<1.0.0,>=0.0.256; extra == 'test'
